tesla_sdk/__init__.py
tesla_sdk/test.py
tesla_sdk/client/__init__.py
tesla_sdk/client/base_client.py
tesla_sdk/client/web/__init__.py
tesla_sdk/client/web/base_web_client.py
tesla_sdk/client/web/charging_client.py
tesla_sdk/client/web/users_client.py
tesla_sdk/client/web/vehicles_client.py
tesla_sdk/client/web/vehicles_command_client.py
tesla_sdk/client/web/web_client.py
tesla_sdk/client/web/errors/__init__.py
teslasdk-0.0.2.dist-info/METADATA
teslasdk-0.0.2.dist-info/WHEEL
teslasdk-0.0.2.dist-info/top_level.txt
teslasdk-0.0.2.dist-info/RECORD
